rtltcp.py
sdrcontrol.py
sdrcontrol.tcss
sdrterm.py
dsp/data_processor.py
dsp/demodulation.py
dsp/dsp_processor.py
dsp/statistics_processor.py
dsp/vfo_processor.py
misc/file_util.py
misc/general_util.py
misc/io_args.py
misc/keyboard_interruptable_thread.py
misc/mappable_enum.py
misc/read_file.py
plots/abstract_plot.py
plots/multi_spectrum_analyzer_plot.py
plots/spectrum_analyzer_plot.py
plots/waterfall_plot.py
sdr/control_rtl_tcp.py
sdr/controller.py
sdr/output_server.py
sdr/receiver.py
sdr/rtl_tcp_commands.py
sdr/socket_receiver.py
sdrterm-0.4.1.dist-info/METADATA
sdrterm-0.4.1.dist-info/WHEEL
sdrterm-0.4.1.dist-info/licenses/LICENSE
sdrterm-0.4.1.dist-info/RECORD
