Metadata-Version: 2.3
Name: sdrterm
Version: 0.4.1
Summary: Terminal-based tools for (mostly SDR-originated) signal analysis
Project-URL: Homepage, https://github.com/peads/sdrterm
Project-URL: Repository, https://github.com/peads/sdrterm.git
Project-URL: Bug Tracker, https://github.com/peads/sdrterm/issues
Author-email: Patrick Eads <peads@users.noreply.github.com>
Maintainer-email: Patrick Eads <peads@users.noreply.github.com>
License:                     GNU GENERAL PUBLIC LICENSE
License-File: LICENSE
Keywords: communications,dsp,radio,rtl,rtl-sdr,rtlsdr,sdr,sdrterm,sigint,signal analysis,signal processing,software-defined radio
Classifier: Development Status :: 4 - Beta
Classifier: Environment :: Console
Classifier: Intended Audience :: Developers
Classifier: Intended Audience :: Science/Research
Classifier: Intended Audience :: Telecommunications Industry
Classifier: License :: OSI Approved :: GNU General Public License v3 (GPLv3)
Classifier: Natural Language :: English
Classifier: Operating System :: Microsoft :: Windows :: Windows 7
Classifier: Operating System :: Microsoft :: Windows :: Windows 8
Classifier: Operating System :: Microsoft :: Windows :: Windows 8.1
Classifier: Operating System :: Microsoft :: Windows :: Windows 10
Classifier: Operating System :: Microsoft :: Windows :: Windows 11
Classifier: Operating System :: POSIX :: Linux
Classifier: Programming Language :: Python :: 3 :: Only
Classifier: Programming Language :: Python :: 3.10
Classifier: Programming Language :: Python :: 3.11
Classifier: Programming Language :: Python :: 3.12
Classifier: Topic :: Multimedia :: Sound/Audio :: Analysis
Classifier: Topic :: Scientific/Engineering :: Mathematics
Classifier: Topic :: Scientific/Engineering :: Physics
Classifier: Topic :: System :: Hardware :: Universal Serial Bus (USB) :: Audio
Classifier: Topic :: System :: Networking
Classifier: Topic :: Utilities
Classifier: Typing :: Typed
Requires-Python: >=3.10
Requires-Dist: numba>=0.60.0
Requires-Dist: numpy>=1.26
Requires-Dist: psutil
Requires-Dist: scipy
Requires-Dist: typer-slim
Provides-Extra: cli
Requires-Dist: textual; extra == 'cli'
Requires-Dist: textual-slider; extra == 'cli'
Provides-Extra: compiled
Requires-Dist: cython; extra == 'compiled'
Requires-Dist: setuptools; extra == 'compiled'
Provides-Extra: gui
Requires-Dist: pyqt5; extra == 'gui'
Requires-Dist: pyqtgraph; extra == 'gui'
